graph_games_model_runner/__init__.py
graph_games_model_runner/fns.py
graph_games_model_runner/main.py
graph_games_model_runner/setup.py
graph_games_model_runner-0.0.191.dist-info/METADATA
graph_games_model_runner-0.0.191.dist-info/WHEEL
graph_games_model_runner-0.0.191.dist-info/top_level.txt
graph_games_model_runner-0.0.191.dist-info/RECORD
