Metadata-Version: 2.4
Name: graph_games_model_runner
Version: 0.0.191
Requires-Dist: multipledispatch==1.0.0
Requires-Dist: torch==2.2.0
Requires-Dist: torch-geometric==2.3.1
Requires-Dist: graph-games-proto==0.3.694
Requires-Dist: pyrsistent==0.20.0
Dynamic: requires-dist
